[{"question": "この城の名前は？", "options": ["姫路城", "松本城", "大阪城", "熊本城"], "answer": "姫路城", "image_url": "C:\\Users\\81802\\OneDrive\\デスクトップ\\絵\\oriba.jpg", "explanation": "あああああああああああああ"}, {"question": "この花の名前は？", "options": ["梅", "桜", "牡丹", "藤"], "answer": "桜", "image_url": "https://upload.wikimedia.org/wikipedia/commons/thumb/3/3f/Japanese_Sakura.JPG/800px-Japanese_Sakura.JPG", "explanation": "ｃｃｃｃｃｃｃｃ"}, {"question": "aaaa", "options": ["aaa", "aa", "a", "c"], "answer": "c", "image_url": "C:\\Users\\81802\\OneDrive\\デスクトップ\\絵\\oriba.jpg", "explanation": "ｗｗｗｗｗ"}]